{"backend_admin_dashboard_specification.md":"f19bd9be","backend_api_documentation.md":"4748dc62","backend_changelog.md":"0cc36186","backend_clean_vm_setup.md":"edd5c7ef","backend_cpanel_user_setup.md":"f52dcbea","backend_cpanel_whm_setup.md":"47b9b8f0","backend_cpanel_whm_setup_v2.md":"4a510ddb","backend_cron_jobs_complete_summary.md":"f3108e31","backend_cron_jobs_dashboard_integration.md":"d3c0d2da","backend_cron_job_dashboard_component.md":"c234e533","backend_custom_headers.md":"c7ce647d","backend_environment_api_keys.md":"70ebcd85","backend_environment_summary.md":"66192827","backend_high_volume_setup.md":"343096f7","backend_multi_environment_setup.md":"3e0198a6","backend_persistence_implemented.md":"67cbd6f0","backend_rate_limit_guide.md":"29e5d168","backend_readme.md":"8140cdaa","backend_tech_stack.md":"0db665e4","backend_test_persistence.md":"607d40a0","backend_unicef_salesforce_middleware_api_documentation.md":"64cd6454","backend_warnings_fixed.md":"e2800906","backend_warning_explanation.md":"4e160d14","backend_environments_readme.md":"a7f9cdea","backend_environments_development_readme.md":"0d60535d","backend_environments_production_readme.md":"2993312e","backend_environments_staging_readme.md":"b6aad779","frontend_api_integration.md":"652e3187","frontend_architecture.md":"e71cd4a5","frontend_changelog.md":"3140cf18","frontend_environment_deployment.md":"4fc823a0","frontend_export_features.md":"cea72134","frontend_monitoring_troubleshooting.md":"e8be8015","frontend_readme.md":"f2bef5e7","frontend_security.md":"5cc9a31c","frontend_security_error_handling.md":"52820cf3","frontend_testing_strategy.md":"33d60c19","frontend_user_guide.md":"80933c1b","index.md":"9632f72e"}
